[
    {
        "id": 1,
        "target_table": "UNDEFINED",
        "target_yaml_id": "QM-30",
        "zref_yaml_id": "0"
    },
    {
        "id": 2,
        "target_table": "UNDEFINED",
        "target_yaml_id": "MA-08",
        "zref_yaml_id": "100"
    },
    {
        "id": 3,
        "target_table": "UNDEFINED",
        "target_yaml_id": "QM-08",
        "zref_yaml_id": "100"
    },
    {
        "id": 4,
        "target_table": "UNDEFINED",
        "target_yaml_id": "QM-53",
        "zref_yaml_id": "100"
    },
    {
        "id": 5,
        "target_table": "UNDEFINED",
        "target_yaml_id": "QM-53-1",
        "zref_yaml_id": "100"
    },
    {
        "id": 6,
        "target_table": "UNDEFINED",
        "target_yaml_id": "QM-53-2",
        "zref_yaml_id": "100"
    },
    {
        "id": 7,
        "target_table": "UNDEFINED",
        "target_yaml_id": "QM-53-3",
        "zref_yaml_id": "100"
    },
    {
        "id": 8,
        "target_table": "UNDEFINED",
        "target_yaml_id": "MA-27",
        "zref_yaml_id": "100"
    },
    {
        "id": 9,
        "target_table": "UNDEFINED",
        "target_yaml_id": "QM-01",
        "zref_yaml_id": "100"
    },
    {
        "id": 10,
        "target_table": "UNDEFINED",
        "target_yaml_id": "MA-29",
        "zref_yaml_id": "100"
    },
    {
        "id": 11,
        "target_table": "UNDEFINED",
        "target_yaml_id": "MA-06",
        "zref_yaml_id": "101"
    },
    {
        "id": 12,
        "target_table": "UNDEFINED",
        "target_yaml_id": "QB-14",
        "zref_yaml_id": "101"
    },
    {
        "id": 13,
        "target_table": "UNDEFINED",
        "target_yaml_id": "QM-25",
        "zref_yaml_id": "102"
    },
    {
        "id": 14,
        "target_table": "UNDEFINED",
        "target_yaml_id": "QM-27",
        "zref_yaml_id": "102"
    },
    {
        "id": 15,
        "target_table": "UNDEFINED",
        "target_yaml_id": "QM-25",
        "zref_yaml_id": "103"
    },
    {
        "id": 16,
        "target_table": "UNDEFINED",
        "target_yaml_id": "QM-18",
        "zref_yaml_id": "104"
    },
    {
        "id": 17,
        "target_table": "UNDEFINED",
        "target_yaml_id": "MA-10",
        "zref_yaml_id": "104"
    },
    {
        "id": 18,
        "target_table": "UNDEFINED",
        "target_yaml_id": "QM-51-11",
        "zref_yaml_id": "107"
    },
    {
        "id": 19,
        "target_table": "UNDEFINED",
        "target_yaml_id": "QM-29",
        "zref_yaml_id": "108"
    },
    {
        "id": 20,
        "target_table": "UNDEFINED",
        "target_yaml_id": "QB-13",
        "zref_yaml_id": "10"
    },
    {
        "id": 21,
        "target_table": "UNDEFINED",
        "target_yaml_id": "QB-01",
        "zref_yaml_id": "10"
    },
    {
        "id": 22,
        "target_table": "UNDEFINED",
        "target_yaml_id": "QB-02",
        "zref_yaml_id": "10"
    },
    {
        "id": 23,
        "target_table": "UNDEFINED",
        "target_yaml_id": "QB-10",
        "zref_yaml_id": "10"
    },
    {
        "id": 24,
        "target_table": "UNDEFINED",
        "target_yaml_id": "QB-12",
        "zref_yaml_id": "10"
    },
    {
        "id": 25,
        "target_table": "UNDEFINED",
        "target_yaml_id": "QB-07",
        "zref_yaml_id": "10"
    },
    {
        "id": 26,
        "target_table": "UNDEFINED",
        "target_yaml_id": "QM-16-2",
        "zref_yaml_id": "110"
    },
    {
        "id": 27,
        "target_table": "UNDEFINED",
        "target_yaml_id": "QM-16-2",
        "zref_yaml_id": "111"
    },
    {
        "id": 28,
        "target_table": "UNDEFINED",
        "target_yaml_id": "QM-16-3",
        "zref_yaml_id": "111"
    },
    {
        "id": 29,
        "target_table": "UNDEFINED",
        "target_yaml_id": "QM-16-4",
        "zref_yaml_id": "111"
    },
    {
        "id": 30,
        "target_table": "UNDEFINED",
        "target_yaml_id": "QM-16",
        "zref_yaml_id": "111"
    },
    {
        "id": 31,
        "target_table": "UNDEFINED",
        "target_yaml_id": "QM-11-4",
        "zref_yaml_id": "113"
    },
    {
        "id": 32,
        "target_table": "UNDEFINED",
        "target_yaml_id": "QM-10",
        "zref_yaml_id": "115"
    },
    {
        "id": 33,
        "target_table": "UNDEFINED",
        "target_yaml_id": "QM-19",
        "zref_yaml_id": "115"
    },
    {
        "id": 34,
        "target_table": "UNDEFINED",
        "target_yaml_id": "QM-21",
        "zref_yaml_id": "115"
    },
    {
        "id": 35,
        "target_table": "UNDEFINED",
        "target_yaml_id": "QM-22",
        "zref_yaml_id": "115"
    },
    {
        "id": 36,
        "target_table": "UNDEFINED",
        "target_yaml_id": "QM-11-5",
        "zref_yaml_id": "116"
    },
    {
        "id": 37,
        "target_table": "UNDEFINED",
        "target_yaml_id": "QM-58",
        "zref_yaml_id": "117"
    },
    {
        "id": 38,
        "target_table": "UNDEFINED",
        "target_yaml_id": "QM-13",
        "zref_yaml_id": "118"
    },
    {
        "id": 39,
        "target_table": "UNDEFINED",
        "target_yaml_id": "QM-16-4",
        "zref_yaml_id": "119"
    },
    {
        "id": 40,
        "target_table": "UNDEFINED",
        "target_yaml_id": "QB-01",
        "zref_yaml_id": "11"
    },
    {
        "id": 41,
        "target_table": "UNDEFINED",
        "target_yaml_id": "QB-02",
        "zref_yaml_id": "11"
    },
    {
        "id": 42,
        "target_table": "UNDEFINED",
        "target_yaml_id": "QB-10",
        "zref_yaml_id": "11"
    },
    {
        "id": 43,
        "target_table": "UNDEFINED",
        "target_yaml_id": "QB-12",
        "zref_yaml_id": "11"
    },
    {
        "id": 44,
        "target_table": "UNDEFINED",
        "target_yaml_id": "QM-51",
        "zref_yaml_id": "120"
    },
    {
        "id": 45,
        "target_table": "UNDEFINED",
        "target_yaml_id": "QM-06",
        "zref_yaml_id": "121"
    },
    {
        "id": 46,
        "target_table": "UNDEFINED",
        "target_yaml_id": "QM-07",
        "zref_yaml_id": "122"
    },
    {
        "id": 47,
        "target_table": "UNDEFINED",
        "target_yaml_id": "QM-16-1",
        "zref_yaml_id": "123"
    },
    {
        "id": 48,
        "target_table": "UNDEFINED",
        "target_yaml_id": "QM-55",
        "zref_yaml_id": "125"
    },
    {
        "id": 49,
        "target_table": "UNDEFINED",
        "target_yaml_id": "QM-07",
        "zref_yaml_id": "126"
    },
    {
        "id": 50,
        "target_table": "UNDEFINED",
        "target_yaml_id": "QM-02",
        "zref_yaml_id": "126"
    },
    {
        "id": 51,
        "target_table": "UNDEFINED",
        "target_yaml_id": "QM-03",
        "zref_yaml_id": "126"
    },
    {
        "id": 52,
        "target_table": "UNDEFINED",
        "target_yaml_id": "QM-04",
        "zref_yaml_id": "126"
    },
    {
        "id": 53,
        "target_table": "UNDEFINED",
        "target_yaml_id": "QM-05",
        "zref_yaml_id": "126"
    },
    {
        "id": 54,
        "target_table": "UNDEFINED",
        "target_yaml_id": "QM-01",
        "zref_yaml_id": "126"
    },
    {
        "id": 55,
        "target_table": "UNDEFINED",
        "target_yaml_id": "QKB-10",
        "zref_yaml_id": "127"
    },
    {
        "id": 56,
        "target_table": "UNDEFINED",
        "target_yaml_id": "QKB-10",
        "zref_yaml_id": "128"
    },
    {
        "id": 57,
        "target_table": "UNDEFINED",
        "target_yaml_id": "QM-62",
        "zref_yaml_id": "128"
    },
    {
        "id": 58,
        "target_table": "UNDEFINED",
        "target_yaml_id": "QM-300",
        "zref_yaml_id": "129"
    },
    {
        "id": 59,
        "target_table": "UNDEFINED",
        "target_yaml_id": "QKB-9",
        "zref_yaml_id": "12"
    },
    {
        "id": 60,
        "target_table": "UNDEFINED",
        "target_yaml_id": "QB-09",
        "zref_yaml_id": "12"
    },
    {
        "id": 61,
        "target_table": "UNDEFINED",
        "target_yaml_id": "QB-15",
        "zref_yaml_id": "131"
    },
    {
        "id": 62,
        "target_table": "UNDEFINED",
        "target_yaml_id": "QM-61-3",
        "zref_yaml_id": "132"
    },
    {
        "id": 63,
        "target_table": "UNDEFINED",
        "target_yaml_id": "QM-58",
        "zref_yaml_id": "135"
    },
    {
        "id": 64,
        "target_table": "UNDEFINED",
        "target_yaml_id": "QM-25",
        "zref_yaml_id": "135"
    },
    {
        "id": 65,
        "target_table": "UNDEFINED",
        "target_yaml_id": "MA-06",
        "zref_yaml_id": "139"
    },
    {
        "id": 66,
        "target_table": "UNDEFINED",
        "target_yaml_id": "MA-18",
        "zref_yaml_id": "140"
    },
    {
        "id": 67,
        "target_table": "UNDEFINED",
        "target_yaml_id": "QB-11",
        "zref_yaml_id": "143"
    },
    {
        "id": 68,
        "target_table": "UNDEFINED",
        "target_yaml_id": "QB-13",
        "zref_yaml_id": "143"
    },
    {
        "id": 69,
        "target_table": "UNDEFINED",
        "target_yaml_id": "QB-12",
        "zref_yaml_id": "143"
    },
    {
        "id": 70,
        "target_table": "UNDEFINED",
        "target_yaml_id": "MA-19",
        "zref_yaml_id": "143"
    },
    {
        "id": 71,
        "target_table": "UNDEFINED",
        "target_yaml_id": "MA-21",
        "zref_yaml_id": "143"
    },
    {
        "id": 72,
        "target_table": "UNDEFINED",
        "target_yaml_id": "QM-62",
        "zref_yaml_id": "143"
    },
    {
        "id": 73,
        "target_table": "UNDEFINED",
        "target_yaml_id": "MA-06",
        "zref_yaml_id": "148"
    },
    {
        "id": 74,
        "target_table": "UNDEFINED",
        "target_yaml_id": "QKB-02",
        "zref_yaml_id": "148"
    },
    {
        "id": 75,
        "target_table": "UNDEFINED",
        "target_yaml_id": "QKB-2",
        "zref_yaml_id": "148"
    },
    {
        "id": 76,
        "target_table": "UNDEFINED",
        "target_yaml_id": "QB-11",
        "zref_yaml_id": "14"
    },
    {
        "id": 77,
        "target_table": "UNDEFINED",
        "target_yaml_id": "MA-22",
        "zref_yaml_id": "14"
    },
    {
        "id": 78,
        "target_table": "UNDEFINED",
        "target_yaml_id": "MA-19",
        "zref_yaml_id": "14"
    },
    {
        "id": 79,
        "target_table": "UNDEFINED",
        "target_yaml_id": "QB-11",
        "zref_yaml_id": "151"
    },
    {
        "id": 80,
        "target_table": "UNDEFINED",
        "target_yaml_id": "MA-22",
        "zref_yaml_id": "151"
    },
    {
        "id": 81,
        "target_table": "UNDEFINED",
        "target_yaml_id": "MA-19",
        "zref_yaml_id": "151"
    },
    {
        "id": 82,
        "target_table": "UNDEFINED",
        "target_yaml_id": "QB-09",
        "zref_yaml_id": "151"
    },
    {
        "id": 83,
        "target_table": "UNDEFINED",
        "target_yaml_id": "QB-11",
        "zref_yaml_id": "153"
    },
    {
        "id": 84,
        "target_table": "UNDEFINED",
        "target_yaml_id": "MA-20",
        "zref_yaml_id": "153"
    },
    {
        "id": 85,
        "target_table": "UNDEFINED",
        "target_yaml_id": "QB-02",
        "zref_yaml_id": "155"
    },
    {
        "id": 86,
        "target_table": "UNDEFINED",
        "target_yaml_id": "QM-44-7",
        "zref_yaml_id": "156"
    },
    {
        "id": 87,
        "target_table": "UNDEFINED",
        "target_yaml_id": "MA-16",
        "zref_yaml_id": "156"
    },
    {
        "id": 88,
        "target_table": "UNDEFINED",
        "target_yaml_id": "QM-44-6",
        "zref_yaml_id": "156"
    },
    {
        "id": 89,
        "target_table": "UNDEFINED",
        "target_yaml_id": "QM-44",
        "zref_yaml_id": "156"
    },
    {
        "id": 90,
        "target_table": "UNDEFINED",
        "target_yaml_id": "QM-44-1",
        "zref_yaml_id": "156"
    },
    {
        "id": 91,
        "target_table": "UNDEFINED",
        "target_yaml_id": "QM-44-2",
        "zref_yaml_id": "156"
    },
    {
        "id": 92,
        "target_table": "UNDEFINED",
        "target_yaml_id": "QM-44-5",
        "zref_yaml_id": "156"
    },
    {
        "id": 93,
        "target_table": "UNDEFINED",
        "target_yaml_id": "QM-44-8",
        "zref_yaml_id": "156"
    },
    {
        "id": 94,
        "target_table": "UNDEFINED",
        "target_yaml_id": "MA-12",
        "zref_yaml_id": "157"
    },
    {
        "id": 95,
        "target_table": "UNDEFINED",
        "target_yaml_id": "MA-23",
        "zref_yaml_id": "157"
    },
    {
        "id": 96,
        "target_table": "UNDEFINED",
        "target_yaml_id": "MA-24",
        "zref_yaml_id": "157"
    },
    {
        "id": 97,
        "target_table": "UNDEFINED",
        "target_yaml_id": "MA-14",
        "zref_yaml_id": "159"
    },
    {
        "id": 98,
        "target_table": "UNDEFINED",
        "target_yaml_id": "MA-19",
        "zref_yaml_id": "15"
    },
    {
        "id": 99,
        "target_table": "UNDEFINED",
        "target_yaml_id": "MA-17",
        "zref_yaml_id": "15"
    },
    {
        "id": 100,
        "target_table": "UNDEFINED",
        "target_yaml_id": "QB-08",
        "zref_yaml_id": "15"
    },
    {
        "id": 101,
        "target_table": "UNDEFINED",
        "target_yaml_id": "QB-06",
        "zref_yaml_id": "160"
    },
    {
        "id": 102,
        "target_table": "UNDEFINED",
        "target_yaml_id": "MA-03",
        "zref_yaml_id": "161"
    },
    {
        "id": 103,
        "target_table": "UNDEFINED",
        "target_yaml_id": "QM-25",
        "zref_yaml_id": "162"
    },
    {
        "id": 104,
        "target_table": "UNDEFINED",
        "target_yaml_id": "QB-05",
        "zref_yaml_id": "163"
    },
    {
        "id": 105,
        "target_table": "UNDEFINED",
        "target_yaml_id": "QKB-09",
        "zref_yaml_id": "164"
    },
    {
        "id": 106,
        "target_table": "UNDEFINED",
        "target_yaml_id": "MA-26",
        "zref_yaml_id": "165"
    },
    {
        "id": 107,
        "target_table": "UNDEFINED",
        "target_yaml_id": "QM-63",
        "zref_yaml_id": "165"
    },
    {
        "id": 108,
        "target_table": "UNDEFINED",
        "target_yaml_id": "QM-63-1",
        "zref_yaml_id": "165"
    },
    {
        "id": 109,
        "target_table": "UNDEFINED",
        "target_yaml_id": "QM-63-2",
        "zref_yaml_id": "165"
    },
    {
        "id": 110,
        "target_table": "UNDEFINED",
        "target_yaml_id": "QM-63-3",
        "zref_yaml_id": "165"
    },
    {
        "id": 111,
        "target_table": "UNDEFINED",
        "target_yaml_id": "QB-07",
        "zref_yaml_id": "167"
    },
    {
        "id": 112,
        "target_table": "UNDEFINED",
        "target_yaml_id": "QB-09",
        "zref_yaml_id": "167"
    },
    {
        "id": 113,
        "target_table": "UNDEFINED",
        "target_yaml_id": "QM-08",
        "zref_yaml_id": "168"
    },
    {
        "id": 114,
        "target_table": "UNDEFINED",
        "target_yaml_id": "MA-18",
        "zref_yaml_id": "169"
    },
    {
        "id": 115,
        "target_table": "UNDEFINED",
        "target_yaml_id": "QB-09",
        "zref_yaml_id": "169"
    },
    {
        "id": 116,
        "target_table": "UNDEFINED",
        "target_yaml_id": "QB-01",
        "zref_yaml_id": "16"
    },
    {
        "id": 117,
        "target_table": "UNDEFINED",
        "target_yaml_id": "QB-02",
        "zref_yaml_id": "16"
    },
    {
        "id": 118,
        "target_table": "UNDEFINED",
        "target_yaml_id": "QKB-2",
        "zref_yaml_id": "16"
    },
    {
        "id": 119,
        "target_table": "UNDEFINED",
        "target_yaml_id": "QKB-3",
        "zref_yaml_id": "16"
    },
    {
        "id": 120,
        "target_table": "UNDEFINED",
        "target_yaml_id": "QKB-4",
        "zref_yaml_id": "16"
    },
    {
        "id": 121,
        "target_table": "UNDEFINED",
        "target_yaml_id": "QB-06",
        "zref_yaml_id": "170"
    },
    {
        "id": 122,
        "target_table": "UNDEFINED",
        "target_yaml_id": "QM-44",
        "zref_yaml_id": "171"
    },
    {
        "id": 123,
        "target_table": "UNDEFINED",
        "target_yaml_id": "QM-58",
        "zref_yaml_id": "172"
    },
    {
        "id": 124,
        "target_table": "UNDEFINED",
        "target_yaml_id": "MA-25",
        "zref_yaml_id": "172"
    },
    {
        "id": 125,
        "target_table": "UNDEFINED",
        "target_yaml_id": "MA-18",
        "zref_yaml_id": "173"
    },
    {
        "id": 126,
        "target_table": "UNDEFINED",
        "target_yaml_id": "MA-19",
        "zref_yaml_id": "173"
    },
    {
        "id": 127,
        "target_table": "UNDEFINED",
        "target_yaml_id": "MA-02",
        "zref_yaml_id": "173"
    },
    {
        "id": 128,
        "target_table": "UNDEFINED",
        "target_yaml_id": "MA-01",
        "zref_yaml_id": "173"
    },
    {
        "id": 129,
        "target_table": "UNDEFINED",
        "target_yaml_id": "MA-03",
        "zref_yaml_id": "173"
    },
    {
        "id": 130,
        "target_table": "UNDEFINED",
        "target_yaml_id": "MA-05",
        "zref_yaml_id": "173"
    },
    {
        "id": 131,
        "target_table": "UNDEFINED",
        "target_yaml_id": "MA-17",
        "zref_yaml_id": "174"
    },
    {
        "id": 132,
        "target_table": "UNDEFINED",
        "target_yaml_id": "QM-45",
        "zref_yaml_id": "174"
    },
    {
        "id": 133,
        "target_table": "UNDEFINED",
        "target_yaml_id": "QB-06",
        "zref_yaml_id": "175"
    },
    {
        "id": 134,
        "target_table": "UNDEFINED",
        "target_yaml_id": "QB-08",
        "zref_yaml_id": "175"
    },
    {
        "id": 135,
        "target_table": "UNDEFINED",
        "target_yaml_id": "QM-59",
        "zref_yaml_id": "175"
    },
    {
        "id": 136,
        "target_table": "UNDEFINED",
        "target_yaml_id": "QM-55",
        "zref_yaml_id": "176"
    },
    {
        "id": 137,
        "target_table": "UNDEFINED",
        "target_yaml_id": "QM-10",
        "zref_yaml_id": "176"
    },
    {
        "id": 138,
        "target_table": "UNDEFINED",
        "target_yaml_id": "QM-19",
        "zref_yaml_id": "176"
    },
    {
        "id": 139,
        "target_table": "UNDEFINED",
        "target_yaml_id": "MA-10",
        "zref_yaml_id": "176"
    },
    {
        "id": 140,
        "target_table": "UNDEFINED",
        "target_yaml_id": "MA-27",
        "zref_yaml_id": "177"
    },
    {
        "id": 141,
        "target_table": "UNDEFINED",
        "target_yaml_id": "MA-11",
        "zref_yaml_id": "178"
    },
    {
        "id": 142,
        "target_table": "UNDEFINED",
        "target_yaml_id": "QB-05",
        "zref_yaml_id": "178"
    },
    {
        "id": 143,
        "target_table": "UNDEFINED",
        "target_yaml_id": "QB-11",
        "zref_yaml_id": "179"
    },
    {
        "id": 144,
        "target_table": "UNDEFINED",
        "target_yaml_id": "MA-19",
        "zref_yaml_id": "179"
    },
    {
        "id": 145,
        "target_table": "UNDEFINED",
        "target_yaml_id": "QB-11",
        "zref_yaml_id": "17"
    },
    {
        "id": 146,
        "target_table": "UNDEFINED",
        "target_yaml_id": "QKB-5",
        "zref_yaml_id": "17"
    },
    {
        "id": 147,
        "target_table": "UNDEFINED",
        "target_yaml_id": "MA-17",
        "zref_yaml_id": "17"
    },
    {
        "id": 148,
        "target_table": "UNDEFINED",
        "target_yaml_id": "QB-06",
        "zref_yaml_id": "17"
    },
    {
        "id": 149,
        "target_table": "UNDEFINED",
        "target_yaml_id": "QB-09",
        "zref_yaml_id": "17"
    },
    {
        "id": 150,
        "target_table": "UNDEFINED",
        "target_yaml_id": "QB-04",
        "zref_yaml_id": "17"
    },
    {
        "id": 151,
        "target_table": "UNDEFINED",
        "target_yaml_id": "QB-13",
        "zref_yaml_id": "180"
    },
    {
        "id": 152,
        "target_table": "UNDEFINED",
        "target_yaml_id": "MA-27",
        "zref_yaml_id": "180"
    },
    {
        "id": 153,
        "target_table": "UNDEFINED",
        "target_yaml_id": "QM-56-3",
        "zref_yaml_id": "180"
    },
    {
        "id": 154,
        "target_table": "UNDEFINED",
        "target_yaml_id": "QM-56-1",
        "zref_yaml_id": "180"
    },
    {
        "id": 155,
        "target_table": "UNDEFINED",
        "target_yaml_id": "QM-56-2",
        "zref_yaml_id": "180"
    },
    {
        "id": 156,
        "target_table": "UNDEFINED",
        "target_yaml_id": "QM-56-4",
        "zref_yaml_id": "180"
    },
    {
        "id": 157,
        "target_table": "UNDEFINED",
        "target_yaml_id": "QM-56-5",
        "zref_yaml_id": "180"
    },
    {
        "id": 158,
        "target_table": "UNDEFINED",
        "target_yaml_id": "QM-26",
        "zref_yaml_id": "180"
    },
    {
        "id": 159,
        "target_table": "UNDEFINED",
        "target_yaml_id": "QM-71",
        "zref_yaml_id": "180"
    },
    {
        "id": 160,
        "target_table": "UNDEFINED",
        "target_yaml_id": "MA-06",
        "zref_yaml_id": "181"
    },
    {
        "id": 161,
        "target_table": "UNDEFINED",
        "target_yaml_id": "MA-19",
        "zref_yaml_id": "181"
    },
    {
        "id": 162,
        "target_table": "UNDEFINED",
        "target_yaml_id": "MA-05",
        "zref_yaml_id": "181"
    },
    {
        "id": 163,
        "target_table": "UNDEFINED",
        "target_yaml_id": "MA-05",
        "zref_yaml_id": "182"
    },
    {
        "id": 164,
        "target_table": "UNDEFINED",
        "target_yaml_id": "QB-13",
        "zref_yaml_id": "183"
    },
    {
        "id": 165,
        "target_table": "UNDEFINED",
        "target_yaml_id": "MA-27",
        "zref_yaml_id": "183"
    },
    {
        "id": 166,
        "target_table": "UNDEFINED",
        "target_yaml_id": "MA-07",
        "zref_yaml_id": "184"
    },
    {
        "id": 167,
        "target_table": "UNDEFINED",
        "target_yaml_id": "MA-06",
        "zref_yaml_id": "185"
    },
    {
        "id": 168,
        "target_table": "UNDEFINED",
        "target_yaml_id": "MA-17",
        "zref_yaml_id": "185"
    },
    {
        "id": 169,
        "target_table": "UNDEFINED",
        "target_yaml_id": "QM-57",
        "zref_yaml_id": "186"
    },
    {
        "id": 170,
        "target_table": "UNDEFINED",
        "target_yaml_id": "QM-57-1",
        "zref_yaml_id": "186"
    },
    {
        "id": 171,
        "target_table": "UNDEFINED",
        "target_yaml_id": "QB-13",
        "zref_yaml_id": "187"
    },
    {
        "id": 172,
        "target_table": "UNDEFINED",
        "target_yaml_id": "QKB-10",
        "zref_yaml_id": "187"
    },
    {
        "id": 173,
        "target_table": "UNDEFINED",
        "target_yaml_id": "MA-16",
        "zref_yaml_id": "188"
    },
    {
        "id": 174,
        "target_table": "UNDEFINED",
        "target_yaml_id": "QB-01",
        "zref_yaml_id": "189"
    },
    {
        "id": 175,
        "target_table": "UNDEFINED",
        "target_yaml_id": "QB-02",
        "zref_yaml_id": "189"
    },
    {
        "id": 176,
        "target_table": "UNDEFINED",
        "target_yaml_id": "QKB-2",
        "zref_yaml_id": "189"
    },
    {
        "id": 177,
        "target_table": "UNDEFINED",
        "target_yaml_id": "QKB-5",
        "zref_yaml_id": "189"
    },
    {
        "id": 178,
        "target_table": "UNDEFINED",
        "target_yaml_id": "QKB-9",
        "zref_yaml_id": "189"
    },
    {
        "id": 179,
        "target_table": "UNDEFINED",
        "target_yaml_id": "QB-05",
        "zref_yaml_id": "189"
    },
    {
        "id": 180,
        "target_table": "UNDEFINED",
        "target_yaml_id": "QB-08",
        "zref_yaml_id": "189"
    },
    {
        "id": 181,
        "target_table": "UNDEFINED",
        "target_yaml_id": "QB-09",
        "zref_yaml_id": "189"
    },
    {
        "id": 182,
        "target_table": "UNDEFINED",
        "target_yaml_id": "QM-62",
        "zref_yaml_id": "189"
    },
    {
        "id": 183,
        "target_table": "UNDEFINED",
        "target_yaml_id": "QKB-2",
        "zref_yaml_id": "18"
    },
    {
        "id": 184,
        "target_table": "UNDEFINED",
        "target_yaml_id": "QKB-3",
        "zref_yaml_id": "18"
    },
    {
        "id": 185,
        "target_table": "UNDEFINED",
        "target_yaml_id": "QKB-4",
        "zref_yaml_id": "18"
    },
    {
        "id": 186,
        "target_table": "UNDEFINED",
        "target_yaml_id": "QB-06",
        "zref_yaml_id": "18"
    },
    {
        "id": 187,
        "target_table": "UNDEFINED",
        "target_yaml_id": "QB-05",
        "zref_yaml_id": "18"
    },
    {
        "id": 188,
        "target_table": "UNDEFINED",
        "target_yaml_id": "QB-01",
        "zref_yaml_id": "190"
    },
    {
        "id": 189,
        "target_table": "UNDEFINED",
        "target_yaml_id": "QB-02",
        "zref_yaml_id": "190"
    },
    {
        "id": 190,
        "target_table": "UNDEFINED",
        "target_yaml_id": "QKB-2",
        "zref_yaml_id": "190"
    },
    {
        "id": 191,
        "target_table": "UNDEFINED",
        "target_yaml_id": "QB-05",
        "zref_yaml_id": "190"
    },
    {
        "id": 192,
        "target_table": "UNDEFINED",
        "target_yaml_id": "QB-08",
        "zref_yaml_id": "190"
    },
    {
        "id": 193,
        "target_table": "UNDEFINED",
        "target_yaml_id": "QB-09",
        "zref_yaml_id": "190"
    },
    {
        "id": 194,
        "target_table": "UNDEFINED",
        "target_yaml_id": "MA-12",
        "zref_yaml_id": "191"
    },
    {
        "id": 195,
        "target_table": "UNDEFINED",
        "target_yaml_id": "MA-13",
        "zref_yaml_id": "191"
    },
    {
        "id": 196,
        "target_table": "UNDEFINED",
        "target_yaml_id": "QB-07",
        "zref_yaml_id": "191"
    },
    {
        "id": 197,
        "target_table": "UNDEFINED",
        "target_yaml_id": "QM-59-3",
        "zref_yaml_id": "191"
    },
    {
        "id": 198,
        "target_table": "UNDEFINED",
        "target_yaml_id": "QB-01",
        "zref_yaml_id": "192"
    },
    {
        "id": 199,
        "target_table": "UNDEFINED",
        "target_yaml_id": "QB-02",
        "zref_yaml_id": "192"
    },
    {
        "id": 200,
        "target_table": "UNDEFINED",
        "target_yaml_id": "QB-08",
        "zref_yaml_id": "192"
    },
    {
        "id": 201,
        "target_table": "UNDEFINED",
        "target_yaml_id": "QB-09",
        "zref_yaml_id": "192"
    },
    {
        "id": 202,
        "target_table": "UNDEFINED",
        "target_yaml_id": "QBK-9",
        "zref_yaml_id": "192"
    },
    {
        "id": 203,
        "target_table": "UNDEFINED",
        "target_yaml_id": "QM-64",
        "zref_yaml_id": "193"
    },
    {
        "id": 204,
        "target_table": "UNDEFINED",
        "target_yaml_id": "MA-27",
        "zref_yaml_id": "194"
    },
    {
        "id": 205,
        "target_table": "UNDEFINED",
        "target_yaml_id": "QM-40",
        "zref_yaml_id": "194"
    },
    {
        "id": 206,
        "target_table": "UNDEFINED",
        "target_yaml_id": "MA-16",
        "zref_yaml_id": "195"
    },
    {
        "id": 207,
        "target_table": "UNDEFINED",
        "target_yaml_id": "MA-27",
        "zref_yaml_id": "196"
    },
    {
        "id": 208,
        "target_table": "UNDEFINED",
        "target_yaml_id": "QM-61-4",
        "zref_yaml_id": "196"
    },
    {
        "id": 209,
        "target_table": "UNDEFINED",
        "target_yaml_id": "QM-38",
        "zref_yaml_id": "196"
    },
    {
        "id": 210,
        "target_table": "UNDEFINED",
        "target_yaml_id": "MA-09",
        "zref_yaml_id": "197"
    },
    {
        "id": 211,
        "target_table": "UNDEFINED",
        "target_yaml_id": "QM-51-9",
        "zref_yaml_id": "197"
    },
    {
        "id": 212,
        "target_table": "UNDEFINED",
        "target_yaml_id": "QM-51-10",
        "zref_yaml_id": "197"
    },
    {
        "id": 213,
        "target_table": "UNDEFINED",
        "target_yaml_id": "QM-58",
        "zref_yaml_id": "198"
    },
    {
        "id": 214,
        "target_table": "UNDEFINED",
        "target_yaml_id": "MA-25",
        "zref_yaml_id": "198"
    },
    {
        "id": 215,
        "target_table": "UNDEFINED",
        "target_yaml_id": "MA-07",
        "zref_yaml_id": "198"
    },
    {
        "id": 216,
        "target_table": "UNDEFINED",
        "target_yaml_id": "QB-11",
        "zref_yaml_id": "199"
    },
    {
        "id": 217,
        "target_table": "UNDEFINED",
        "target_yaml_id": "MA-20",
        "zref_yaml_id": "199"
    },
    {
        "id": 218,
        "target_table": "UNDEFINED",
        "target_yaml_id": "QB-14",
        "zref_yaml_id": "199"
    },
    {
        "id": 219,
        "target_table": "UNDEFINED",
        "target_yaml_id": "QB-11",
        "zref_yaml_id": "19"
    },
    {
        "id": 220,
        "target_table": "UNDEFINED",
        "target_yaml_id": "QB-13",
        "zref_yaml_id": "19"
    },
    {
        "id": 221,
        "target_table": "UNDEFINED",
        "target_yaml_id": "QB-12",
        "zref_yaml_id": "19"
    },
    {
        "id": 222,
        "target_table": "UNDEFINED",
        "target_yaml_id": "QB-06",
        "zref_yaml_id": "19"
    },
    {
        "id": 223,
        "target_table": "UNDEFINED",
        "target_yaml_id": "QB-05",
        "zref_yaml_id": "19"
    },
    {
        "id": 224,
        "target_table": "UNDEFINED",
        "target_yaml_id": "QB-09",
        "zref_yaml_id": "19"
    },
    {
        "id": 225,
        "target_table": "UNDEFINED",
        "target_yaml_id": "QB-04",
        "zref_yaml_id": "19"
    },
    {
        "id": 226,
        "target_table": "UNDEFINED",
        "target_yaml_id": "QB-09",
        "zref_yaml_id": "1"
    },
    {
        "id": 227,
        "target_table": "UNDEFINED",
        "target_yaml_id": "QM-70",
        "zref_yaml_id": "200"
    },
    {
        "id": 228,
        "target_table": "UNDEFINED",
        "target_yaml_id": "MA-27",
        "zref_yaml_id": "201"
    },
    {
        "id": 229,
        "target_table": "UNDEFINED",
        "target_yaml_id": "QM-28",
        "zref_yaml_id": "201"
    },
    {
        "id": 230,
        "target_table": "UNDEFINED",
        "target_yaml_id": "QB-06",
        "zref_yaml_id": "202"
    },
    {
        "id": 231,
        "target_table": "UNDEFINED",
        "target_yaml_id": "MA-27",
        "zref_yaml_id": "202"
    },
    {
        "id": 232,
        "target_table": "UNDEFINED",
        "target_yaml_id": "QM-16-3",
        "zref_yaml_id": "203"
    },
    {
        "id": 233,
        "target_table": "UNDEFINED",
        "target_yaml_id": "QM-16",
        "zref_yaml_id": "203"
    },
    {
        "id": 234,
        "target_table": "UNDEFINED",
        "target_yaml_id": "QM-44",
        "zref_yaml_id": "204"
    },
    {
        "id": 235,
        "target_table": "UNDEFINED",
        "target_yaml_id": "QB-11",
        "zref_yaml_id": "206"
    },
    {
        "id": 236,
        "target_table": "UNDEFINED",
        "target_yaml_id": "QB-13",
        "zref_yaml_id": "206"
    },
    {
        "id": 237,
        "target_table": "UNDEFINED",
        "target_yaml_id": "QKB-04",
        "zref_yaml_id": "206"
    },
    {
        "id": 238,
        "target_table": "UNDEFINED",
        "target_yaml_id": "QKB-2",
        "zref_yaml_id": "206"
    },
    {
        "id": 239,
        "target_table": "UNDEFINED",
        "target_yaml_id": "QKB-5",
        "zref_yaml_id": "206"
    },
    {
        "id": 240,
        "target_table": "UNDEFINED",
        "target_yaml_id": "MA-21",
        "zref_yaml_id": "206"
    },
    {
        "id": 241,
        "target_table": "UNDEFINED",
        "target_yaml_id": "MA-17",
        "zref_yaml_id": "206"
    },
    {
        "id": 242,
        "target_table": "UNDEFINED",
        "target_yaml_id": "QKB-10",
        "zref_yaml_id": "206"
    },
    {
        "id": 243,
        "target_table": "UNDEFINED",
        "target_yaml_id": "QB-05",
        "zref_yaml_id": "206"
    },
    {
        "id": 244,
        "target_table": "UNDEFINED",
        "target_yaml_id": "MA-18",
        "zref_yaml_id": "207"
    },
    {
        "id": 245,
        "target_table": "UNDEFINED",
        "target_yaml_id": "QB-11",
        "zref_yaml_id": "208"
    },
    {
        "id": 246,
        "target_table": "UNDEFINED",
        "target_yaml_id": "QB-14",
        "zref_yaml_id": "208"
    },
    {
        "id": 247,
        "target_table": "UNDEFINED",
        "target_yaml_id": "MA-18",
        "zref_yaml_id": "209"
    },
    {
        "id": 248,
        "target_table": "UNDEFINED",
        "target_yaml_id": "QB-04",
        "zref_yaml_id": "20"
    },
    {
        "id": 249,
        "target_table": "UNDEFINED",
        "target_yaml_id": "MA-18",
        "zref_yaml_id": "210"
    },
    {
        "id": 250,
        "target_table": "UNDEFINED",
        "target_yaml_id": "QB-11",
        "zref_yaml_id": "211"
    },
    {
        "id": 251,
        "target_table": "UNDEFINED",
        "target_yaml_id": "QB-13",
        "zref_yaml_id": "211"
    },
    {
        "id": 252,
        "target_table": "UNDEFINED",
        "target_yaml_id": "QM-44",
        "zref_yaml_id": "212"
    },
    {
        "id": 253,
        "target_table": "UNDEFINED",
        "target_yaml_id": "QB-11",
        "zref_yaml_id": "213"
    },
    {
        "id": 254,
        "target_table": "UNDEFINED",
        "target_yaml_id": "MA-17",
        "zref_yaml_id": "214"
    },
    {
        "id": 255,
        "target_table": "UNDEFINED",
        "target_yaml_id": "MA-27",
        "zref_yaml_id": "215"
    },
    {
        "id": 256,
        "target_table": "UNDEFINED",
        "target_yaml_id": "MA-21",
        "zref_yaml_id": "216"
    },
    {
        "id": 257,
        "target_table": "UNDEFINED",
        "target_yaml_id": "QM-51-8",
        "zref_yaml_id": "217"
    },
    {
        "id": 258,
        "target_table": "UNDEFINED",
        "target_yaml_id": "QM-52-03",
        "zref_yaml_id": "217"
    },
    {
        "id": 259,
        "target_table": "UNDEFINED",
        "target_yaml_id": "QM-52-07",
        "zref_yaml_id": "217"
    },
    {
        "id": 260,
        "target_table": "UNDEFINED",
        "target_yaml_id": "QM-52-06",
        "zref_yaml_id": "217"
    },
    {
        "id": 261,
        "target_table": "UNDEFINED",
        "target_yaml_id": "QM-52-05",
        "zref_yaml_id": "217"
    },
    {
        "id": 262,
        "target_table": "UNDEFINED",
        "target_yaml_id": "QM-52",
        "zref_yaml_id": "217"
    },
    {
        "id": 263,
        "target_table": "UNDEFINED",
        "target_yaml_id": "QM-42",
        "zref_yaml_id": "217"
    },
    {
        "id": 264,
        "target_table": "UNDEFINED",
        "target_yaml_id": "QM-24",
        "zref_yaml_id": "217"
    },
    {
        "id": 265,
        "target_table": "UNDEFINED",
        "target_yaml_id": "QM-20",
        "zref_yaml_id": "217"
    },
    {
        "id": 266,
        "target_table": "UNDEFINED",
        "target_yaml_id": "QM-51-7",
        "zref_yaml_id": "217"
    },
    {
        "id": 267,
        "target_table": "UNDEFINED",
        "target_yaml_id": "QM-51-9",
        "zref_yaml_id": "217"
    },
    {
        "id": 268,
        "target_table": "UNDEFINED",
        "target_yaml_id": "QM-51-5",
        "zref_yaml_id": "217"
    },
    {
        "id": 269,
        "target_table": "UNDEFINED",
        "target_yaml_id": "QM-51-4",
        "zref_yaml_id": "217"
    },
    {
        "id": 270,
        "target_table": "UNDEFINED",
        "target_yaml_id": "QM-51-3",
        "zref_yaml_id": "217"
    },
    {
        "id": 271,
        "target_table": "UNDEFINED",
        "target_yaml_id": "QM-51-6",
        "zref_yaml_id": "217"
    },
    {
        "id": 272,
        "target_table": "UNDEFINED",
        "target_yaml_id": "QM-51-2",
        "zref_yaml_id": "217"
    },
    {
        "id": 273,
        "target_table": "UNDEFINED",
        "target_yaml_id": "QM-51-1",
        "zref_yaml_id": "217"
    },
    {
        "id": 274,
        "target_table": "UNDEFINED",
        "target_yaml_id": "QM-52-04",
        "zref_yaml_id": "217"
    },
    {
        "id": 275,
        "target_table": "UNDEFINED",
        "target_yaml_id": "QM-52-01",
        "zref_yaml_id": "217"
    },
    {
        "id": 276,
        "target_table": "UNDEFINED",
        "target_yaml_id": "QM-52-02",
        "zref_yaml_id": "217"
    },
    {
        "id": 277,
        "target_table": "UNDEFINED",
        "target_yaml_id": "QM-40",
        "zref_yaml_id": "217"
    },
    {
        "id": 278,
        "target_table": "UNDEFINED",
        "target_yaml_id": "QM-33",
        "zref_yaml_id": "218"
    },
    {
        "id": 279,
        "target_table": "UNDEFINED",
        "target_yaml_id": "MA-01",
        "zref_yaml_id": "219"
    },
    {
        "id": 280,
        "target_table": "UNDEFINED",
        "target_yaml_id": "QB-11",
        "zref_yaml_id": "21"
    },
    {
        "id": 281,
        "target_table": "UNDEFINED",
        "target_yaml_id": "MA-22",
        "zref_yaml_id": "21"
    },
    {
        "id": 282,
        "target_table": "UNDEFINED",
        "target_yaml_id": "MA-19",
        "zref_yaml_id": "21"
    },
    {
        "id": 283,
        "target_table": "UNDEFINED",
        "target_yaml_id": "MA-21",
        "zref_yaml_id": "21"
    },
    {
        "id": 284,
        "target_table": "UNDEFINED",
        "target_yaml_id": "MA-21",
        "zref_yaml_id": "220"
    },
    {
        "id": 285,
        "target_table": "UNDEFINED",
        "target_yaml_id": "QKB-9",
        "zref_yaml_id": "221"
    },
    {
        "id": 286,
        "target_table": "UNDEFINED",
        "target_yaml_id": "MA-18",
        "zref_yaml_id": "221"
    },
    {
        "id": 287,
        "target_table": "UNDEFINED",
        "target_yaml_id": "QB-09",
        "zref_yaml_id": "221"
    },
    {
        "id": 288,
        "target_table": "UNDEFINED",
        "target_yaml_id": "MA-05",
        "zref_yaml_id": "222"
    },
    {
        "id": 289,
        "target_table": "UNDEFINED",
        "target_yaml_id": "QKB-9",
        "zref_yaml_id": "223"
    },
    {
        "id": 290,
        "target_table": "UNDEFINED",
        "target_yaml_id": "QKB-10",
        "zref_yaml_id": "223"
    },
    {
        "id": 291,
        "target_table": "UNDEFINED",
        "target_yaml_id": "QM-10",
        "zref_yaml_id": "224"
    },
    {
        "id": 292,
        "target_table": "UNDEFINED",
        "target_yaml_id": "QM-10-2",
        "zref_yaml_id": "224"
    },
    {
        "id": 293,
        "target_table": "UNDEFINED",
        "target_yaml_id": "QB-11",
        "zref_yaml_id": "225"
    },
    {
        "id": 294,
        "target_table": "UNDEFINED",
        "target_yaml_id": "MA-21",
        "zref_yaml_id": "225"
    },
    {
        "id": 295,
        "target_table": "UNDEFINED",
        "target_yaml_id": "QB-09",
        "zref_yaml_id": "225"
    },
    {
        "id": 296,
        "target_table": "UNDEFINED",
        "target_yaml_id": "QM-65",
        "zref_yaml_id": "226"
    },
    {
        "id": 297,
        "target_table": "UNDEFINED",
        "target_yaml_id": "MA-18",
        "zref_yaml_id": "227"
    },
    {
        "id": 298,
        "target_table": "UNDEFINED",
        "target_yaml_id": "MA-22",
        "zref_yaml_id": "227"
    },
    {
        "id": 299,
        "target_table": "UNDEFINED",
        "target_yaml_id": "MA-21",
        "zref_yaml_id": "227"
    },
    {
        "id": 300,
        "target_table": "UNDEFINED",
        "target_yaml_id": "MA-20",
        "zref_yaml_id": "227"
    },
    {
        "id": 301,
        "target_table": "UNDEFINED",
        "target_yaml_id": "QM-29",
        "zref_yaml_id": "228"
    },
    {
        "id": 302,
        "target_table": "UNDEFINED",
        "target_yaml_id": "MA-10",
        "zref_yaml_id": "228"
    },
    {
        "id": 303,
        "target_table": "UNDEFINED",
        "target_yaml_id": "MA-02",
        "zref_yaml_id": "229"
    },
    {
        "id": 304,
        "target_table": "UNDEFINED",
        "target_yaml_id": "QB-06",
        "zref_yaml_id": "22"
    },
    {
        "id": 305,
        "target_table": "UNDEFINED",
        "target_yaml_id": "QB-09",
        "zref_yaml_id": "22"
    },
    {
        "id": 306,
        "target_table": "UNDEFINED",
        "target_yaml_id": "QB-06",
        "zref_yaml_id": "230"
    },
    {
        "id": 307,
        "target_table": "UNDEFINED",
        "target_yaml_id": "QB-08",
        "zref_yaml_id": "230"
    },
    {
        "id": 308,
        "target_table": "UNDEFINED",
        "target_yaml_id": "QB-04",
        "zref_yaml_id": "230"
    },
    {
        "id": 309,
        "target_table": "UNDEFINED",
        "target_yaml_id": "QB-15",
        "zref_yaml_id": "230"
    },
    {
        "id": 310,
        "target_table": "UNDEFINED",
        "target_yaml_id": "QB-11",
        "zref_yaml_id": "231"
    },
    {
        "id": 311,
        "target_table": "UNDEFINED",
        "target_yaml_id": "QM-30",
        "zref_yaml_id": "233"
    },
    {
        "id": 312,
        "target_table": "UNDEFINED",
        "target_yaml_id": "QM-30",
        "zref_yaml_id": "234"
    },
    {
        "id": 313,
        "target_table": "UNDEFINED",
        "target_yaml_id": "QB-11",
        "zref_yaml_id": "235"
    },
    {
        "id": 314,
        "target_table": "UNDEFINED",
        "target_yaml_id": "MA-21",
        "zref_yaml_id": "235"
    },
    {
        "id": 315,
        "target_table": "UNDEFINED",
        "target_yaml_id": "QB-06",
        "zref_yaml_id": "235"
    },
    {
        "id": 316,
        "target_table": "UNDEFINED",
        "target_yaml_id": "QB-09",
        "zref_yaml_id": "235"
    },
    {
        "id": 317,
        "target_table": "UNDEFINED",
        "target_yaml_id": "QM-62",
        "zref_yaml_id": "235"
    },
    {
        "id": 318,
        "target_table": "UNDEFINED",
        "target_yaml_id": "QB-11",
        "zref_yaml_id": "236"
    },
    {
        "id": 319,
        "target_table": "UNDEFINED",
        "target_yaml_id": "QB-09",
        "zref_yaml_id": "236"
    },
    {
        "id": 320,
        "target_table": "UNDEFINED",
        "target_yaml_id": "MA-22",
        "zref_yaml_id": "237"
    },
    {
        "id": 321,
        "target_table": "UNDEFINED",
        "target_yaml_id": "QB-12",
        "zref_yaml_id": "237"
    },
    {
        "id": 322,
        "target_table": "UNDEFINED",
        "target_yaml_id": "MA-21",
        "zref_yaml_id": "237"
    },
    {
        "id": 323,
        "target_table": "UNDEFINED",
        "target_yaml_id": "QB-06",
        "zref_yaml_id": "237"
    },
    {
        "id": 324,
        "target_table": "UNDEFINED",
        "target_yaml_id": "QB-09",
        "zref_yaml_id": "237"
    },
    {
        "id": 325,
        "target_table": "UNDEFINED",
        "target_yaml_id": "QM-49",
        "zref_yaml_id": "238"
    },
    {
        "id": 326,
        "target_table": "UNDEFINED",
        "target_yaml_id": "QM-16-2",
        "zref_yaml_id": "239"
    },
    {
        "id": 327,
        "target_table": "UNDEFINED",
        "target_yaml_id": "QM-16-3",
        "zref_yaml_id": "239"
    },
    {
        "id": 328,
        "target_table": "UNDEFINED",
        "target_yaml_id": "QM-16-4",
        "zref_yaml_id": "239"
    },
    {
        "id": 329,
        "target_table": "UNDEFINED",
        "target_yaml_id": "QB-14",
        "zref_yaml_id": "23"
    },
    {
        "id": 330,
        "target_table": "UNDEFINED",
        "target_yaml_id": "QM-41",
        "zref_yaml_id": "240"
    },
    {
        "id": 331,
        "target_table": "UNDEFINED",
        "target_yaml_id": "QM-09",
        "zref_yaml_id": "240"
    },
    {
        "id": 332,
        "target_table": "UNDEFINED",
        "target_yaml_id": "QM-16-1",
        "zref_yaml_id": "241"
    },
    {
        "id": 333,
        "target_table": "UNDEFINED",
        "target_yaml_id": "QM-48",
        "zref_yaml_id": "242"
    },
    {
        "id": 334,
        "target_table": "UNDEFINED",
        "target_yaml_id": "QM-23",
        "zref_yaml_id": "243"
    },
    {
        "id": 335,
        "target_table": "UNDEFINED",
        "target_yaml_id": "QM-11-1",
        "zref_yaml_id": "244"
    },
    {
        "id": 336,
        "target_table": "UNDEFINED",
        "target_yaml_id": "QM-19",
        "zref_yaml_id": "245"
    },
    {
        "id": 337,
        "target_table": "UNDEFINED",
        "target_yaml_id": "QM-08",
        "zref_yaml_id": "246"
    },
    {
        "id": 338,
        "target_table": "UNDEFINED",
        "target_yaml_id": "MA-22",
        "zref_yaml_id": "247"
    },
    {
        "id": 339,
        "target_table": "UNDEFINED",
        "target_yaml_id": "MA-19",
        "zref_yaml_id": "247"
    },
    {
        "id": 340,
        "target_table": "UNDEFINED",
        "target_yaml_id": "MA-17",
        "zref_yaml_id": "247"
    },
    {
        "id": 341,
        "target_table": "UNDEFINED",
        "target_yaml_id": "MA-20",
        "zref_yaml_id": "247"
    },
    {
        "id": 342,
        "target_table": "UNDEFINED",
        "target_yaml_id": "QB-09",
        "zref_yaml_id": "247"
    },
    {
        "id": 343,
        "target_table": "UNDEFINED",
        "target_yaml_id": "QM-50",
        "zref_yaml_id": "248"
    },
    {
        "id": 344,
        "target_table": "UNDEFINED",
        "target_yaml_id": "QM-44-4",
        "zref_yaml_id": "248"
    },
    {
        "id": 345,
        "target_table": "UNDEFINED",
        "target_yaml_id": "QM-44-6",
        "zref_yaml_id": "248"
    },
    {
        "id": 346,
        "target_table": "UNDEFINED",
        "target_yaml_id": "QM-13",
        "zref_yaml_id": "249"
    },
    {
        "id": 347,
        "target_table": "UNDEFINED",
        "target_yaml_id": "QB-13",
        "zref_yaml_id": "24"
    },
    {
        "id": 348,
        "target_table": "UNDEFINED",
        "target_yaml_id": "QB-02",
        "zref_yaml_id": "24"
    },
    {
        "id": 349,
        "target_table": "UNDEFINED",
        "target_yaml_id": "QKB-09",
        "zref_yaml_id": "24"
    },
    {
        "id": 350,
        "target_table": "UNDEFINED",
        "target_yaml_id": "QKB-9",
        "zref_yaml_id": "24"
    },
    {
        "id": 351,
        "target_table": "UNDEFINED",
        "target_yaml_id": "QB-10",
        "zref_yaml_id": "24"
    },
    {
        "id": 352,
        "target_table": "UNDEFINED",
        "target_yaml_id": "QB-12",
        "zref_yaml_id": "24"
    },
    {
        "id": 353,
        "target_table": "UNDEFINED",
        "target_yaml_id": "QM-35",
        "zref_yaml_id": "250"
    },
    {
        "id": 354,
        "target_table": "UNDEFINED",
        "target_yaml_id": "MA-16",
        "zref_yaml_id": "252"
    },
    {
        "id": 355,
        "target_table": "UNDEFINED",
        "target_yaml_id": "QM-44",
        "zref_yaml_id": "252"
    },
    {
        "id": 356,
        "target_table": "UNDEFINED",
        "target_yaml_id": "QM-32",
        "zref_yaml_id": "253"
    },
    {
        "id": 357,
        "target_table": "UNDEFINED",
        "target_yaml_id": "QM-15",
        "zref_yaml_id": "253"
    },
    {
        "id": 358,
        "target_table": "UNDEFINED",
        "target_yaml_id": "MA-17",
        "zref_yaml_id": "254"
    },
    {
        "id": 359,
        "target_table": "UNDEFINED",
        "target_yaml_id": "QM-47",
        "zref_yaml_id": "255"
    },
    {
        "id": 360,
        "target_table": "UNDEFINED",
        "target_yaml_id": "MA-12",
        "zref_yaml_id": "256"
    },
    {
        "id": 361,
        "target_table": "UNDEFINED",
        "target_yaml_id": "MA-14",
        "zref_yaml_id": "256"
    },
    {
        "id": 362,
        "target_table": "UNDEFINED",
        "target_yaml_id": "QKB-09",
        "zref_yaml_id": "257"
    },
    {
        "id": 363,
        "target_table": "UNDEFINED",
        "target_yaml_id": "MA-18",
        "zref_yaml_id": "257"
    },
    {
        "id": 364,
        "target_table": "UNDEFINED",
        "target_yaml_id": "QB-09",
        "zref_yaml_id": "257"
    },
    {
        "id": 365,
        "target_table": "UNDEFINED",
        "target_yaml_id": "QM-11-2",
        "zref_yaml_id": "258"
    },
    {
        "id": 366,
        "target_table": "UNDEFINED",
        "target_yaml_id": "QM-16",
        "zref_yaml_id": "258"
    },
    {
        "id": 367,
        "target_table": "UNDEFINED",
        "target_yaml_id": "QM-11-1",
        "zref_yaml_id": "258"
    },
    {
        "id": 368,
        "target_table": "UNDEFINED",
        "target_yaml_id": "QM-51",
        "zref_yaml_id": "259"
    },
    {
        "id": 369,
        "target_table": "UNDEFINED",
        "target_yaml_id": "QKB-2",
        "zref_yaml_id": "25"
    },
    {
        "id": 370,
        "target_table": "UNDEFINED",
        "target_yaml_id": "QB-05",
        "zref_yaml_id": "25"
    },
    {
        "id": 371,
        "target_table": "UNDEFINED",
        "target_yaml_id": "QB-09",
        "zref_yaml_id": "25"
    },
    {
        "id": 372,
        "target_table": "UNDEFINED",
        "target_yaml_id": "QB-03",
        "zref_yaml_id": "25"
    },
    {
        "id": 373,
        "target_table": "UNDEFINED",
        "target_yaml_id": "QKB-2",
        "zref_yaml_id": "260"
    },
    {
        "id": 374,
        "target_table": "UNDEFINED",
        "target_yaml_id": "QKB-5",
        "zref_yaml_id": "260"
    },
    {
        "id": 375,
        "target_table": "UNDEFINED",
        "target_yaml_id": "QKB-01",
        "zref_yaml_id": "260"
    },
    {
        "id": 376,
        "target_table": "UNDEFINED",
        "target_yaml_id": "QM-62",
        "zref_yaml_id": "260"
    },
    {
        "id": 377,
        "target_table": "UNDEFINED",
        "target_yaml_id": "MA-21",
        "zref_yaml_id": "261"
    },
    {
        "id": 378,
        "target_table": "UNDEFINED",
        "target_yaml_id": "QM-25-1",
        "zref_yaml_id": "262"
    },
    {
        "id": 379,
        "target_table": "UNDEFINED",
        "target_yaml_id": "QM-13",
        "zref_yaml_id": "263"
    },
    {
        "id": 380,
        "target_table": "UNDEFINED",
        "target_yaml_id": "QM-10-3",
        "zref_yaml_id": "264"
    },
    {
        "id": 381,
        "target_table": "UNDEFINED",
        "target_yaml_id": "MA-17",
        "zref_yaml_id": "265"
    },
    {
        "id": 382,
        "target_table": "UNDEFINED",
        "target_yaml_id": "QM-46",
        "zref_yaml_id": "267"
    },
    {
        "id": 383,
        "target_table": "UNDEFINED",
        "target_yaml_id": "QM-30",
        "zref_yaml_id": "268"
    },
    {
        "id": 384,
        "target_table": "UNDEFINED",
        "target_yaml_id": "MA-20",
        "zref_yaml_id": "269"
    },
    {
        "id": 385,
        "target_table": "UNDEFINED",
        "target_yaml_id": "QM-66",
        "zref_yaml_id": "270"
    },
    {
        "id": 386,
        "target_table": "UNDEFINED",
        "target_yaml_id": "MA-18",
        "zref_yaml_id": "272"
    },
    {
        "id": 387,
        "target_table": "UNDEFINED",
        "target_yaml_id": "MA-17",
        "zref_yaml_id": "272"
    },
    {
        "id": 388,
        "target_table": "UNDEFINED",
        "target_yaml_id": "MA-18",
        "zref_yaml_id": "273"
    },
    {
        "id": 389,
        "target_table": "UNDEFINED",
        "target_yaml_id": "MA-17",
        "zref_yaml_id": "273"
    },
    {
        "id": 390,
        "target_table": "UNDEFINED",
        "target_yaml_id": "MA-18",
        "zref_yaml_id": "274"
    },
    {
        "id": 391,
        "target_table": "UNDEFINED",
        "target_yaml_id": "MA-17",
        "zref_yaml_id": "274"
    },
    {
        "id": 392,
        "target_table": "UNDEFINED",
        "target_yaml_id": "QB-09",
        "zref_yaml_id": "274"
    },
    {
        "id": 393,
        "target_table": "UNDEFINED",
        "target_yaml_id": "QM-44-9",
        "zref_yaml_id": "275"
    },
    {
        "id": 394,
        "target_table": "UNDEFINED",
        "target_yaml_id": "QM-07",
        "zref_yaml_id": "276"
    },
    {
        "id": 395,
        "target_table": "UNDEFINED",
        "target_yaml_id": "QM-03",
        "zref_yaml_id": "276"
    },
    {
        "id": 396,
        "target_table": "UNDEFINED",
        "target_yaml_id": "QM-04",
        "zref_yaml_id": "276"
    },
    {
        "id": 397,
        "target_table": "UNDEFINED",
        "target_yaml_id": "QM-05",
        "zref_yaml_id": "276"
    },
    {
        "id": 398,
        "target_table": "UNDEFINED",
        "target_yaml_id": "QM-06",
        "zref_yaml_id": "276"
    },
    {
        "id": 399,
        "target_table": "UNDEFINED",
        "target_yaml_id": "MA-27",
        "zref_yaml_id": "276"
    },
    {
        "id": 400,
        "target_table": "UNDEFINED",
        "target_yaml_id": "QM-12",
        "zref_yaml_id": "276"
    },
    {
        "id": 401,
        "target_table": "UNDEFINED",
        "target_yaml_id": "QM-35",
        "zref_yaml_id": "276"
    },
    {
        "id": 402,
        "target_table": "UNDEFINED",
        "target_yaml_id": "QM-37",
        "zref_yaml_id": "276"
    },
    {
        "id": 403,
        "target_table": "UNDEFINED",
        "target_yaml_id": "QM-68-1",
        "zref_yaml_id": "277"
    },
    {
        "id": 404,
        "target_table": "UNDEFINED",
        "target_yaml_id": "QM-68-3",
        "zref_yaml_id": "279"
    },
    {
        "id": 405,
        "target_table": "UNDEFINED",
        "target_yaml_id": "QB-11",
        "zref_yaml_id": "27"
    },
    {
        "id": 406,
        "target_table": "UNDEFINED",
        "target_yaml_id": "MA-17",
        "zref_yaml_id": "27"
    },
    {
        "id": 407,
        "target_table": "UNDEFINED",
        "target_yaml_id": "MA-20",
        "zref_yaml_id": "27"
    },
    {
        "id": 408,
        "target_table": "UNDEFINED",
        "target_yaml_id": "QM-68-4",
        "zref_yaml_id": "280"
    },
    {
        "id": 409,
        "target_table": "UNDEFINED",
        "target_yaml_id": "MA-28",
        "zref_yaml_id": "280"
    },
    {
        "id": 410,
        "target_table": "UNDEFINED",
        "target_yaml_id": "QM-68-5",
        "zref_yaml_id": "281"
    },
    {
        "id": 411,
        "target_table": "UNDEFINED",
        "target_yaml_id": "QM-68-6",
        "zref_yaml_id": "283"
    },
    {
        "id": 412,
        "target_table": "UNDEFINED",
        "target_yaml_id": "QB-11",
        "zref_yaml_id": "284"
    },
    {
        "id": 413,
        "target_table": "UNDEFINED",
        "target_yaml_id": "QM-62",
        "zref_yaml_id": "284"
    },
    {
        "id": 414,
        "target_table": "UNDEFINED",
        "target_yaml_id": "QM-36",
        "zref_yaml_id": "285"
    },
    {
        "id": 415,
        "target_table": "UNDEFINED",
        "target_yaml_id": "QM-69-2",
        "zref_yaml_id": "286"
    },
    {
        "id": 416,
        "target_table": "UNDEFINED",
        "target_yaml_id": "MA-18",
        "zref_yaml_id": "287"
    },
    {
        "id": 417,
        "target_table": "UNDEFINED",
        "target_yaml_id": "QM-67",
        "zref_yaml_id": "287"
    },
    {
        "id": 418,
        "target_table": "UNDEFINED",
        "target_yaml_id": "QM-59",
        "zref_yaml_id": "288"
    },
    {
        "id": 419,
        "target_table": "UNDEFINED",
        "target_yaml_id": "QM-59-3",
        "zref_yaml_id": "288"
    },
    {
        "id": 420,
        "target_table": "UNDEFINED",
        "target_yaml_id": "QM-59-1",
        "zref_yaml_id": "288"
    },
    {
        "id": 421,
        "target_table": "UNDEFINED",
        "target_yaml_id": "QM-59",
        "zref_yaml_id": "289"
    },
    {
        "id": 422,
        "target_table": "UNDEFINED",
        "target_yaml_id": "QM-59-3",
        "zref_yaml_id": "289"
    },
    {
        "id": 423,
        "target_table": "UNDEFINED",
        "target_yaml_id": "QM-59-1",
        "zref_yaml_id": "289"
    },
    {
        "id": 424,
        "target_table": "UNDEFINED",
        "target_yaml_id": "MA-22",
        "zref_yaml_id": "28"
    },
    {
        "id": 425,
        "target_table": "UNDEFINED",
        "target_yaml_id": "QB-06",
        "zref_yaml_id": "28"
    },
    {
        "id": 426,
        "target_table": "UNDEFINED",
        "target_yaml_id": "QB-05",
        "zref_yaml_id": "28"
    },
    {
        "id": 427,
        "target_table": "UNDEFINED",
        "target_yaml_id": "QB-04",
        "zref_yaml_id": "28"
    },
    {
        "id": 428,
        "target_table": "UNDEFINED",
        "target_yaml_id": "QM-56-3",
        "zref_yaml_id": "290"
    },
    {
        "id": 429,
        "target_table": "UNDEFINED",
        "target_yaml_id": "QM-56-7",
        "zref_yaml_id": "290"
    },
    {
        "id": 430,
        "target_table": "UNDEFINED",
        "target_yaml_id": "QM-61-1",
        "zref_yaml_id": "291"
    },
    {
        "id": 431,
        "target_table": "UNDEFINED",
        "target_yaml_id": "QM-54-2",
        "zref_yaml_id": "291"
    },
    {
        "id": 432,
        "target_table": "UNDEFINED",
        "target_yaml_id": "QM-54-3",
        "zref_yaml_id": "291"
    },
    {
        "id": 433,
        "target_table": "UNDEFINED",
        "target_yaml_id": "QM-54-1",
        "zref_yaml_id": "291"
    },
    {
        "id": 434,
        "target_table": "UNDEFINED",
        "target_yaml_id": "MA-25",
        "zref_yaml_id": "292"
    },
    {
        "id": 435,
        "target_table": "UNDEFINED",
        "target_yaml_id": "QM-58-2",
        "zref_yaml_id": "292"
    },
    {
        "id": 436,
        "target_table": "UNDEFINED",
        "target_yaml_id": "QM-58-1",
        "zref_yaml_id": "292"
    },
    {
        "id": 437,
        "target_table": "UNDEFINED",
        "target_yaml_id": "QM-43",
        "zref_yaml_id": "293"
    },
    {
        "id": 438,
        "target_table": "UNDEFINED",
        "target_yaml_id": "QM-39",
        "zref_yaml_id": "294"
    },
    {
        "id": 439,
        "target_table": "UNDEFINED",
        "target_yaml_id": "QM-68-2",
        "zref_yaml_id": "295"
    },
    {
        "id": 440,
        "target_table": "UNDEFINED",
        "target_yaml_id": "QKB-02",
        "zref_yaml_id": "296"
    },
    {
        "id": 441,
        "target_table": "UNDEFINED",
        "target_yaml_id": "MA-18",
        "zref_yaml_id": "296"
    },
    {
        "id": 442,
        "target_table": "UNDEFINED",
        "target_yaml_id": "QKB-10",
        "zref_yaml_id": "296"
    },
    {
        "id": 443,
        "target_table": "UNDEFINED",
        "target_yaml_id": "MA-20",
        "zref_yaml_id": "296"
    },
    {
        "id": 444,
        "target_table": "UNDEFINED",
        "target_yaml_id": "QB-06",
        "zref_yaml_id": "296"
    },
    {
        "id": 445,
        "target_table": "UNDEFINED",
        "target_yaml_id": "QKB-01",
        "zref_yaml_id": "296"
    },
    {
        "id": 446,
        "target_table": "UNDEFINED",
        "target_yaml_id": "QB-15",
        "zref_yaml_id": "296"
    },
    {
        "id": 447,
        "target_table": "UNDEFINED",
        "target_yaml_id": "MA-30",
        "zref_yaml_id": "296"
    },
    {
        "id": 448,
        "target_table": "UNDEFINED",
        "target_yaml_id": "MA-20",
        "zref_yaml_id": "297"
    },
    {
        "id": 449,
        "target_table": "UNDEFINED",
        "target_yaml_id": "QM-51",
        "zref_yaml_id": "298"
    },
    {
        "id": 450,
        "target_table": "UNDEFINED",
        "target_yaml_id": "QM-59-2",
        "zref_yaml_id": "299"
    },
    {
        "id": 451,
        "target_table": "UNDEFINED",
        "target_yaml_id": "QB-12",
        "zref_yaml_id": "29"
    },
    {
        "id": 452,
        "target_table": "UNDEFINED",
        "target_yaml_id": "QB-01",
        "zref_yaml_id": "2"
    },
    {
        "id": 453,
        "target_table": "UNDEFINED",
        "target_yaml_id": "QB-02",
        "zref_yaml_id": "2"
    },
    {
        "id": 454,
        "target_table": "UNDEFINED",
        "target_yaml_id": "QKB-02",
        "zref_yaml_id": "2"
    },
    {
        "id": 455,
        "target_table": "UNDEFINED",
        "target_yaml_id": "QKB-03",
        "zref_yaml_id": "2"
    },
    {
        "id": 456,
        "target_table": "UNDEFINED",
        "target_yaml_id": "QKB-04",
        "zref_yaml_id": "2"
    },
    {
        "id": 457,
        "target_table": "UNDEFINED",
        "target_yaml_id": "QKB-05",
        "zref_yaml_id": "2"
    },
    {
        "id": 458,
        "target_table": "UNDEFINED",
        "target_yaml_id": "QKB-09",
        "zref_yaml_id": "2"
    },
    {
        "id": 459,
        "target_table": "UNDEFINED",
        "target_yaml_id": "QKB-2",
        "zref_yaml_id": "2"
    },
    {
        "id": 460,
        "target_table": "UNDEFINED",
        "target_yaml_id": "QKB-3",
        "zref_yaml_id": "2"
    },
    {
        "id": 461,
        "target_table": "UNDEFINED",
        "target_yaml_id": "QKB-4",
        "zref_yaml_id": "2"
    },
    {
        "id": 462,
        "target_table": "UNDEFINED",
        "target_yaml_id": "QKB-5",
        "zref_yaml_id": "2"
    },
    {
        "id": 463,
        "target_table": "UNDEFINED",
        "target_yaml_id": "QKB-9",
        "zref_yaml_id": "2"
    },
    {
        "id": 464,
        "target_table": "UNDEFINED",
        "target_yaml_id": "QB-03",
        "zref_yaml_id": "2"
    },
    {
        "id": 465,
        "target_table": "UNDEFINED",
        "target_yaml_id": "QM-59-2",
        "zref_yaml_id": "300"
    },
    {
        "id": 466,
        "target_table": "UNDEFINED",
        "target_yaml_id": "QM-62",
        "zref_yaml_id": "301"
    },
    {
        "id": 467,
        "target_table": "UNDEFINED",
        "target_yaml_id": "QM-57-2",
        "zref_yaml_id": "302"
    },
    {
        "id": 468,
        "target_table": "UNDEFINED",
        "target_yaml_id": "QM-68-1",
        "zref_yaml_id": "303"
    },
    {
        "id": 469,
        "target_table": "UNDEFINED",
        "target_yaml_id": "QM-69-2",
        "zref_yaml_id": "304"
    },
    {
        "id": 470,
        "target_table": "UNDEFINED",
        "target_yaml_id": "QM-69-1",
        "zref_yaml_id": "304"
    },
    {
        "id": 471,
        "target_table": "UNDEFINED",
        "target_yaml_id": "QM-45",
        "zref_yaml_id": "305"
    },
    {
        "id": 472,
        "target_table": "UNDEFINED",
        "target_yaml_id": "MA-30",
        "zref_yaml_id": "306"
    },
    {
        "id": 473,
        "target_table": "UNDEFINED",
        "target_yaml_id": "QB-11",
        "zref_yaml_id": "30"
    },
    {
        "id": 474,
        "target_table": "UNDEFINED",
        "target_yaml_id": "QB-01",
        "zref_yaml_id": "31"
    },
    {
        "id": 475,
        "target_table": "UNDEFINED",
        "target_yaml_id": "QB-02",
        "zref_yaml_id": "31"
    },
    {
        "id": 476,
        "target_table": "UNDEFINED",
        "target_yaml_id": "MA-02",
        "zref_yaml_id": "31"
    },
    {
        "id": 477,
        "target_table": "UNDEFINED",
        "target_yaml_id": "MA-01",
        "zref_yaml_id": "31"
    },
    {
        "id": 478,
        "target_table": "UNDEFINED",
        "target_yaml_id": "MA-03",
        "zref_yaml_id": "31"
    },
    {
        "id": 479,
        "target_table": "UNDEFINED",
        "target_yaml_id": "MA-05",
        "zref_yaml_id": "31"
    },
    {
        "id": 480,
        "target_table": "UNDEFINED",
        "target_yaml_id": "MA-06",
        "zref_yaml_id": "33"
    },
    {
        "id": 481,
        "target_table": "UNDEFINED",
        "target_yaml_id": "QB-01",
        "zref_yaml_id": "33"
    },
    {
        "id": 482,
        "target_table": "UNDEFINED",
        "target_yaml_id": "QKB-04",
        "zref_yaml_id": "33"
    },
    {
        "id": 483,
        "target_table": "UNDEFINED",
        "target_yaml_id": "QKB-2",
        "zref_yaml_id": "33"
    },
    {
        "id": 484,
        "target_table": "UNDEFINED",
        "target_yaml_id": "QKB-3",
        "zref_yaml_id": "33"
    },
    {
        "id": 485,
        "target_table": "UNDEFINED",
        "target_yaml_id": "QKB-4",
        "zref_yaml_id": "33"
    },
    {
        "id": 486,
        "target_table": "UNDEFINED",
        "target_yaml_id": "QKB-5",
        "zref_yaml_id": "33"
    },
    {
        "id": 487,
        "target_table": "UNDEFINED",
        "target_yaml_id": "QKB-9",
        "zref_yaml_id": "33"
    },
    {
        "id": 488,
        "target_table": "UNDEFINED",
        "target_yaml_id": "QKB-6",
        "zref_yaml_id": "33"
    },
    {
        "id": 489,
        "target_table": "UNDEFINED",
        "target_yaml_id": "QKB-7",
        "zref_yaml_id": "33"
    },
    {
        "id": 490,
        "target_table": "UNDEFINED",
        "target_yaml_id": "QKB-8",
        "zref_yaml_id": "33"
    },
    {
        "id": 491,
        "target_table": "UNDEFINED",
        "target_yaml_id": "QB-08",
        "zref_yaml_id": "33"
    },
    {
        "id": 492,
        "target_table": "UNDEFINED",
        "target_yaml_id": "QKB-01",
        "zref_yaml_id": "33"
    },
    {
        "id": 493,
        "target_table": "UNDEFINED",
        "target_yaml_id": "MA-20",
        "zref_yaml_id": "34"
    },
    {
        "id": 494,
        "target_table": "UNDEFINED",
        "target_yaml_id": "QM-31",
        "zref_yaml_id": "34"
    },
    {
        "id": 495,
        "target_table": "UNDEFINED",
        "target_yaml_id": "QKB-9",
        "zref_yaml_id": "36"
    },
    {
        "id": 496,
        "target_table": "UNDEFINED",
        "target_yaml_id": "MA-22",
        "zref_yaml_id": "36"
    },
    {
        "id": 497,
        "target_table": "UNDEFINED",
        "target_yaml_id": "MA-19",
        "zref_yaml_id": "36"
    },
    {
        "id": 498,
        "target_table": "UNDEFINED",
        "target_yaml_id": "QKB-10",
        "zref_yaml_id": "36"
    },
    {
        "id": 499,
        "target_table": "UNDEFINED",
        "target_yaml_id": "QM-17",
        "zref_yaml_id": "36"
    },
    {
        "id": 500,
        "target_table": "UNDEFINED",
        "target_yaml_id": "QM-62",
        "zref_yaml_id": "36"
    },
    {
        "id": 501,
        "target_table": "UNDEFINED",
        "target_yaml_id": "QB-03",
        "zref_yaml_id": "37"
    },
    {
        "id": 502,
        "target_table": "UNDEFINED",
        "target_yaml_id": "QB-11",
        "zref_yaml_id": "38"
    },
    {
        "id": 503,
        "target_table": "UNDEFINED",
        "target_yaml_id": "MA-20",
        "zref_yaml_id": "38"
    },
    {
        "id": 504,
        "target_table": "UNDEFINED",
        "target_yaml_id": "QM-31",
        "zref_yaml_id": "39"
    },
    {
        "id": 505,
        "target_table": "UNDEFINED",
        "target_yaml_id": "MA-18",
        "zref_yaml_id": "3"
    },
    {
        "id": 506,
        "target_table": "UNDEFINED",
        "target_yaml_id": "QB-09",
        "zref_yaml_id": "3"
    },
    {
        "id": 507,
        "target_table": "UNDEFINED",
        "target_yaml_id": "MA-22",
        "zref_yaml_id": "40"
    },
    {
        "id": 508,
        "target_table": "UNDEFINED",
        "target_yaml_id": "QB-06",
        "zref_yaml_id": "40"
    },
    {
        "id": 509,
        "target_table": "UNDEFINED",
        "target_yaml_id": "QB-05",
        "zref_yaml_id": "40"
    },
    {
        "id": 510,
        "target_table": "UNDEFINED",
        "target_yaml_id": "QB-03",
        "zref_yaml_id": "40"
    },
    {
        "id": 511,
        "target_table": "UNDEFINED",
        "target_yaml_id": "QB-13",
        "zref_yaml_id": "4"
    },
    {
        "id": 512,
        "target_table": "UNDEFINED",
        "target_yaml_id": "MA-22",
        "zref_yaml_id": "4"
    },
    {
        "id": 513,
        "target_table": "UNDEFINED",
        "target_yaml_id": "QB-10",
        "zref_yaml_id": "4"
    },
    {
        "id": 514,
        "target_table": "UNDEFINED",
        "target_yaml_id": "QB-12",
        "zref_yaml_id": "4"
    },
    {
        "id": 515,
        "target_table": "UNDEFINED",
        "target_yaml_id": "MA-18",
        "zref_yaml_id": "52"
    },
    {
        "id": 516,
        "target_table": "UNDEFINED",
        "target_yaml_id": "QM-60",
        "zref_yaml_id": "52"
    },
    {
        "id": 517,
        "target_table": "UNDEFINED",
        "target_yaml_id": "QB-11",
        "zref_yaml_id": "54"
    },
    {
        "id": 518,
        "target_table": "UNDEFINED",
        "target_yaml_id": "MA-18",
        "zref_yaml_id": "55"
    },
    {
        "id": 519,
        "target_table": "UNDEFINED",
        "target_yaml_id": "QB-11",
        "zref_yaml_id": "56"
    },
    {
        "id": 520,
        "target_table": "UNDEFINED",
        "target_yaml_id": "QB-13",
        "zref_yaml_id": "56"
    },
    {
        "id": 521,
        "target_table": "UNDEFINED",
        "target_yaml_id": "QB-06",
        "zref_yaml_id": "56"
    },
    {
        "id": 522,
        "target_table": "UNDEFINED",
        "target_yaml_id": "QB-11",
        "zref_yaml_id": "57"
    },
    {
        "id": 523,
        "target_table": "UNDEFINED",
        "target_yaml_id": "QM-11-2",
        "zref_yaml_id": "59"
    },
    {
        "id": 524,
        "target_table": "UNDEFINED",
        "target_yaml_id": "QM-11-3",
        "zref_yaml_id": "59"
    },
    {
        "id": 525,
        "target_table": "UNDEFINED",
        "target_yaml_id": "QM-10",
        "zref_yaml_id": "61"
    },
    {
        "id": 526,
        "target_table": "UNDEFINED",
        "target_yaml_id": "QM-19",
        "zref_yaml_id": "61"
    },
    {
        "id": 527,
        "target_table": "UNDEFINED",
        "target_yaml_id": "QM-25",
        "zref_yaml_id": "62"
    },
    {
        "id": 528,
        "target_table": "UNDEFINED",
        "target_yaml_id": "QB-09",
        "zref_yaml_id": "6"
    },
    {
        "id": 529,
        "target_table": "UNDEFINED",
        "target_yaml_id": "MA-11",
        "zref_yaml_id": "71"
    },
    {
        "id": 530,
        "target_table": "UNDEFINED",
        "target_yaml_id": "MA-12",
        "zref_yaml_id": "72"
    },
    {
        "id": 531,
        "target_table": "UNDEFINED",
        "target_yaml_id": "MA-09",
        "zref_yaml_id": "73"
    },
    {
        "id": 532,
        "target_table": "UNDEFINED",
        "target_yaml_id": "MA-02",
        "zref_yaml_id": "74"
    },
    {
        "id": 533,
        "target_table": "UNDEFINED",
        "target_yaml_id": "MA-04",
        "zref_yaml_id": "74"
    },
    {
        "id": 534,
        "target_table": "UNDEFINED",
        "target_yaml_id": "QM-44-7",
        "zref_yaml_id": "76"
    },
    {
        "id": 535,
        "target_table": "UNDEFINED",
        "target_yaml_id": "QM-58",
        "zref_yaml_id": "77"
    },
    {
        "id": 536,
        "target_table": "UNDEFINED",
        "target_yaml_id": "MA-25",
        "zref_yaml_id": "77"
    },
    {
        "id": 537,
        "target_table": "UNDEFINED",
        "target_yaml_id": "QM-58-3",
        "zref_yaml_id": "77"
    },
    {
        "id": 538,
        "target_table": "UNDEFINED",
        "target_yaml_id": "QM-56-6",
        "zref_yaml_id": "79"
    },
    {
        "id": 539,
        "target_table": "UNDEFINED",
        "target_yaml_id": "QB-11",
        "zref_yaml_id": "7"
    },
    {
        "id": 540,
        "target_table": "UNDEFINED",
        "target_yaml_id": "MA-22",
        "zref_yaml_id": "7"
    },
    {
        "id": 541,
        "target_table": "UNDEFINED",
        "target_yaml_id": "MA-19",
        "zref_yaml_id": "7"
    },
    {
        "id": 542,
        "target_table": "UNDEFINED",
        "target_yaml_id": "MA-21",
        "zref_yaml_id": "7"
    },
    {
        "id": 543,
        "target_table": "UNDEFINED",
        "target_yaml_id": "QB-09",
        "zref_yaml_id": "7"
    },
    {
        "id": 544,
        "target_table": "UNDEFINED",
        "target_yaml_id": "QM-29",
        "zref_yaml_id": "81"
    },
    {
        "id": 545,
        "target_table": "UNDEFINED",
        "target_yaml_id": "QM-54-2",
        "zref_yaml_id": "81"
    },
    {
        "id": 546,
        "target_table": "UNDEFINED",
        "target_yaml_id": "MA-10",
        "zref_yaml_id": "81"
    },
    {
        "id": 547,
        "target_table": "UNDEFINED",
        "target_yaml_id": "QM-55",
        "zref_yaml_id": "82"
    },
    {
        "id": 548,
        "target_table": "UNDEFINED",
        "target_yaml_id": "QM-10",
        "zref_yaml_id": "82"
    },
    {
        "id": 549,
        "target_table": "UNDEFINED",
        "target_yaml_id": "QM-19",
        "zref_yaml_id": "82"
    },
    {
        "id": 550,
        "target_table": "UNDEFINED",
        "target_yaml_id": "QM-44-6",
        "zref_yaml_id": "83"
    },
    {
        "id": 551,
        "target_table": "UNDEFINED",
        "target_yaml_id": "QM-44",
        "zref_yaml_id": "83"
    },
    {
        "id": 552,
        "target_table": "UNDEFINED",
        "target_yaml_id": "QM-50",
        "zref_yaml_id": "84"
    },
    {
        "id": 553,
        "target_table": "UNDEFINED",
        "target_yaml_id": "QM-44-4",
        "zref_yaml_id": "84"
    },
    {
        "id": 554,
        "target_table": "UNDEFINED",
        "target_yaml_id": "QM-44-6",
        "zref_yaml_id": "84"
    },
    {
        "id": 555,
        "target_table": "UNDEFINED",
        "target_yaml_id": "QM-44-1",
        "zref_yaml_id": "84"
    },
    {
        "id": 556,
        "target_table": "UNDEFINED",
        "target_yaml_id": "QM-44-2",
        "zref_yaml_id": "84"
    },
    {
        "id": 557,
        "target_table": "UNDEFINED",
        "target_yaml_id": "QM-44-3",
        "zref_yaml_id": "84"
    },
    {
        "id": 558,
        "target_table": "UNDEFINED",
        "target_yaml_id": "MA-22",
        "zref_yaml_id": "86"
    },
    {
        "id": 559,
        "target_table": "UNDEFINED",
        "target_yaml_id": "MA-23",
        "zref_yaml_id": "89"
    },
    {
        "id": 560,
        "target_table": "UNDEFINED",
        "target_yaml_id": "MA-24",
        "zref_yaml_id": "89"
    },
    {
        "id": 561,
        "target_table": "UNDEFINED",
        "target_yaml_id": "QB-11",
        "zref_yaml_id": "8"
    },
    {
        "id": 562,
        "target_table": "UNDEFINED",
        "target_yaml_id": "QB-10",
        "zref_yaml_id": "8"
    },
    {
        "id": 563,
        "target_table": "UNDEFINED",
        "target_yaml_id": "QM-15",
        "zref_yaml_id": "92"
    },
    {
        "id": 564,
        "target_table": "UNDEFINED",
        "target_yaml_id": "MA-13",
        "zref_yaml_id": "96"
    },
    {
        "id": 565,
        "target_table": "UNDEFINED",
        "target_yaml_id": "QM-50",
        "zref_yaml_id": "96"
    },
    {
        "id": 566,
        "target_table": "UNDEFINED",
        "target_yaml_id": "QM-59-3",
        "zref_yaml_id": "96"
    },
    {
        "id": 567,
        "target_table": "UNDEFINED",
        "target_yaml_id": "MA-14",
        "zref_yaml_id": "97"
    },
    {
        "id": 568,
        "target_table": "UNDEFINED",
        "target_yaml_id": "MA-15",
        "zref_yaml_id": "97"
    },
    {
        "id": 569,
        "target_table": "UNDEFINED",
        "target_yaml_id": "MA-16",
        "zref_yaml_id": "97"
    },
    {
        "id": 570,
        "target_table": "UNDEFINED",
        "target_yaml_id": "MA-14",
        "zref_yaml_id": "98"
    }
]